{
    "2": {
        "title": "Win 11 Pro Double -Screen Laptop 15.6\u2019\u2019 High -Speed Celeron N5105(2.0GHz) Quad Core Processor FHD IPS Screen Notebook 16GB RAM 512GB SSD with Color Backlight Keyboard 180\u00b0Opening and Closing(16+512GB)  ",
        "price": "$469.88",
        "ratings": [
            "3.6 out of 5 stars",
            "51"
        ],
        "product_link": "www.amazon.com/sspa/click?ie=UTF8&spc=MTozMDM3ODEyMTczMzkxNjY5OjE2OTg4ODI4NzA6c3BfYXRmX25leHQ6MjAwMTQyODE5NTQ2MTk4OjowOjo&url=%2FProcessor-Notebook-Backlight-Keyboard-180%25C2%25B0Opening%2Fdp%2FB0BYS8KLDY%2Fref%3Dsr_1_18_sspa%3Fcrid%3D2Z3FBHRWW5C7D%26keywords%3Dmacbook%26qid%3D1698882870%26sprefix%3Dmacbo%252Caps%252C250%26sr%3D8-18-spons%26sp_csd%3Dd2lkZ2V0TmFtZT1zcF9hdGZfbmV4dA%26psc%3D1",
        "img_src": "https://m.media-amazon.com/images/I/71L6HDw7+RL._AC_UY218_.jpg"
    },
    "3": {
        "title": "Apple 2022 MacBook Pro M2 Chip (13-inch, 8GB RAM, 256GB SSD Storage) (QWERTY English) Space Gray (Renewed Premium)  ",
        "price": "$959.00",
        "ratings": [
            "4.1 out of 5 stars",
            "7"
        ],
        "product_link": "www.amazon.com/Apple-MacBook-13-inch-Storage-English/dp/B0CB7619C5/ref=sr_1_3?crid=2Z3FBHRWW5C7D&keywords=macbook&qid=1698882858&sprefix=macbo%2Caps%2C250&sr=8-3",
        "img_src": "https://m.media-amazon.com/images/I/61L5QgPvgqL._AC_UY218_.jpg"
    },
    "4": {
        "title": "Apple MacBook Air 13.3\" with Retina Display, M1 Chip with 8-Core CPU and 7-Core GPU, 16GB Memory, 1TB SSD, Space Gray, Late 2020  ",
        "price": "$1,599.00",
        "ratings": [
            "2.8 out of 5 stars",
            "4"
        ],
        "product_link": "www.amazon.com/Apple-MacBook-Retina-Display-8-Core/dp/B091V35QM9/ref=sr_1_20?crid=2Z3FBHRWW5C7D&keywords=macbook&qid=1698882870&sprefix=macbo%2Caps%2C250&sr=8-20",
        "img_src": "https://m.media-amazon.com/images/I/513hdiS0EIL._AC_UY218_.jpg"
    },
    "5": {
        "title": "Apple 2021 MacBook Pro (16-inch, M1 Pro chip with 10\u2011core CPU and 16\u2011core GPU, 32GB RAM, 512GB SSD) - Space Gray Z14V0016E  ",
        "price": "$1,999.00",
        "ratings": [
            "4.7 out of 5 stars",
            "57"
        ],
        "product_link": "www.amazon.com/Apple-MacBook-16-inch-10%E2%80%91core-16%E2%80%91core/dp/B09MSRJ97Y/ref=sr_1_5?crid=2Z3FBHRWW5C7D&keywords=macbook&qid=1698882858&sprefix=macbo%2Caps%2C250&sr=8-5",
        "img_src": "https://m.media-amazon.com/images/I/61aUBxqc5PL._AC_UY218_.jpg"
    },
    "6": {
        "title": "Early 2020 Apple MacBook Air with 1.1GHz Core i3 (13 inch, 8GB RAM, 256GB SSD) Space Gray (Renewed)  ",
        "price": "$535.00",
        "ratings": [
            "4.2 out of 5 stars",
            "356"
        ],
        "product_link": "www.amazon.com/Apple-MacBook-13-inch-256GB-Storage/dp/B08CCKVS59/ref=sr_1_6?crid=2Z3FBHRWW5C7D&keywords=macbook&qid=1698882858&sprefix=macbo%2Caps%2C250&sr=8-6",
        "img_src": "https://m.media-amazon.com/images/I/717n9H3RSxL._AC_UY218_.jpg"
    },
    "7": {
        "title": "Apple 2023 MacBook Pro Laptop M2 Pro chip with 10\u2011core CPU and 16\u2011core GPU: 14.2-inch Liquid Retina XDR Display, 16GB Unified Memory, 512GB SSD Storage. Works with iPhone/iPad; Space Gray  ",
        "price": "2 capacities",
        "ratings": [
            "4.7 out of 5 stars",
            "463"
        ],
        "product_link": "www.amazon.com/Apple-MacBook-Laptop-10%E2%80%91core-16%E2%80%91core/dp/B0BSHDVBXZ/ref=sr_1_23?crid=2Z3FBHRWW5C7D&keywords=macbook&qid=1698882870&sprefix=macbo%2Caps%2C250&sr=8-23",
        "img_src": "https://m.media-amazon.com/images/I/61lYIKPieDL._AC_UY218_.jpg"
    },
    "10": {
        "title": "USB C Adapter for MacBook Pro/Air M1 M2 2021 2020 2019 2018,MOKiN USB C Hub MacBook Pro Accessories with 3 USB 3.0 Ports,USB C to SD/TF Card Reader and 100W Thunderbolt 3 PD Port  ",
        "price": "$18.98",
        "ratings": [
            "4.4 out of 5 stars",
            "7,429"
        ],
        "product_link": "www.amazon.com/Adapter-MacBook-Accessories-Adapters-Reader/dp/B07Z4FP2VX/ref=sr_1_26?crid=2Z3FBHRWW5C7D&keywords=macbook&qid=1698882870&sprefix=macbo%2Caps%2C250&sr=8-26",
        "img_src": "https://m.media-amazon.com/images/I/71bNCnPa--L._AC_UY218_.jpg"
    },
    "11": {
        "title": "Apple 2022 MacBook Air Laptop with M2 chip: 13.6-inch Liquid Retina Display, 8GB RAM, 512GB SSD Storage, Backlit Keyboard, 1080p FaceTime HD Camera. Works with iPhone and iPad; Starlight  ",
        "price": "2 capacities",
        "ratings": [
            "4.8 out of 5 stars",
            "2,264"
        ],
        "product_link": "www.amazon.com/2022-Apple-MacBook-Laptop-chip/dp/B0B3BVKXH8/ref=sr_1_27?crid=2Z3FBHRWW5C7D&keywords=macbook&qid=1698882870&sprefix=macbo%2Caps%2C250&sr=8-27",
        "img_src": "https://m.media-amazon.com/images/I/710TJuHTMhL._AC_UY218_.jpg"
    },
    "12": {
        "title": "MOSISO Compatible with MacBook Air 13 inch Case 2022, 2021-2018 Release A2337 M1 A2179 A1932 Retina Display Touch ID, Plastic Hard Shell&Keyboard Cover&Screen Protector&Storage Bag, Transparent  ",
        "price": "$12.79",
        "ratings": [
            "4.3 out of 5 stars",
            "51,058"
        ],
        "product_link": "www.amazon.com/MOSISO-MacBook-Keyboard-Protector-Compatible/dp/B07KG6TR7X/ref=sr_1_28?crid=2Z3FBHRWW5C7D&keywords=macbook&qid=1698882870&sprefix=macbo%2Caps%2C250&sr=8-28",
        "img_src": "https://m.media-amazon.com/images/I/51A2y8WC7mL._AC_UY218_.jpg"
    },
    "13": {
        "title": "Microsoft Surface Pro 3 (128 GB, Intel Core i5) (Renewed)  ",
        "price": "$230.00",
        "ratings": [
            "3.7 out of 5 stars",
            "907"
        ],
        "product_link": "www.amazon.com/Microsoft-Surface-Intel-Core-Renewed/dp/B00TUJ7WQW/ref=sr_1_29?crid=2Z3FBHRWW5C7D&keywords=macbook&qid=1698882870&sprefix=macbo%2Caps%2C250&sr=8-29",
        "img_src": "https://m.media-amazon.com/images/I/71BYhQ+lTuL._AC_UY218_.jpg"
    },
    "14": {
        "title": "ApoloSign 15.6'' Laptop Computer, Quad-Core Intel Celeron N5095 Processors, 12GB DDR4, 512GB SSD, 1080P FHD Display, Windows 11 Laptops Computers, Ultra Slim, 170\u00b0 Open AngleI, Long Battery Life  ",
        "price": "$329.99",
        "ratings": [
            "4.7 out of 5 stars",
            "49"
        ],
        "product_link": "www.amazon.com/ApoloSign-Computer-Quad-Core-Processors-Computers/dp/B0CCP4DV8C/ref=sr_1_30?crid=2Z3FBHRWW5C7D&keywords=macbook&qid=1698882870&sprefix=macbo%2Caps%2C250&sr=8-30",
        "img_src": "https://m.media-amazon.com/images/I/71vEXQierYL._AC_UY218_.jpg"
    },
    "1": {
        "title": "HP 2022 Premium 14-inch HD Thin and Light Laptop, Intel Quad-Core Processor, 32GB RAM, 64GB Storage, Long Battery Life, Webcam, Bluetooth, HDMI, Wi-Fi, Rose Gold, Windows 11 + 1 Year Microsoft 365  ",
        "price": "$349.00",
        "ratings": [
            "4.2 out of 5 stars",
            "2,200"
        ],
        "product_link": "www.amazon.com/sspa/click?ie=UTF8&spc=MTozMDM3ODEyMTczMzkxNjY5OjE2OTg4ODI4NzA6c3BfYXRmX25leHQ6MjAwMTEyMzI3NDA2Mjk4OjowOjo&url=%2FHP-Premium-Quad-Core-Processor-Bluetooth%2Fdp%2FB0B9HWFMCX%2Fref%3Dsr_1_17_sspa%3Fcrid%3D2Z3FBHRWW5C7D%26keywords%3Dmacbook%26qid%3D1698882870%26sprefix%3Dmacbo%252Caps%252C250%26sr%3D8-17-spons%26sp_csd%3Dd2lkZ2V0TmFtZT1zcF9hdGZfbmV4dA%26psc%3D1",
        "img_src": "https://m.media-amazon.com/images/I/71OzuOh5oQL._AC_UY218_.jpg"
    },
    "15": {
        "title": "Apple MacBook Pro 16.2\" with Liquid Retina XDR Display, M2 Max Chip with 12-Core CPU and 38-Core GPU, 64GB Memory, 1TB SSD, Space Gray, Early 2023  ",
        "price": "$3,799.00",
        "ratings": [
            "5.0 out of 5 stars",
            "1"
        ],
        "product_link": "www.amazon.com/Apple-MacBook-Pro-Early-2023/dp/B0BZFNLQ4B/ref=sr_1_31?crid=2Z3FBHRWW5C7D&keywords=macbook&qid=1698882870&sprefix=macbo%2Caps%2C250&sr=8-31",
        "img_src": "https://m.media-amazon.com/images/I/51fVpA-sVfL._AC_UY218_.jpg"
    },
    "16": {
        "title": "Mac Book Pro Charger - 118W USB C Charger Fast Charger for MacBook Pro, MacBook Air, iPad Pro, Samsung Galaxy and All USB-C Devices, 7.2ft USB C to C Cable  ",
        "price": "$36.99",
        "ratings": [
            "4.6 out of 5 stars",
            "3,668"
        ],
        "product_link": "www.amazon.com/Mac-Book-Pro-Charger-MacBook/dp/B09GFR7NSK/ref=sr_1_32?crid=2Z3FBHRWW5C7D&keywords=macbook&qid=1698882870&sprefix=macbo%2Caps%2C250&sr=8-32",
        "img_src": "https://m.media-amazon.com/images/I/519YBPLrKCL._AC_UY218_.jpg"
    }
}